FACTS.py
MANIFEST.in
README.md
setup.py
experiments/temp_exp/config.yml
experiments/temp_exp/resource.yml
experiments/temp_exp/input/readme
modules/genmod/directsample/genmod_preprocess_directsample.py
modules/genmod/directsample/genmod_project_directsample.py
modules/genmod/directsample/pipeline.yml
modules/gilford/icesheets/gilford_calibrate_icesheets.py
modules/gilford/icesheets/gilford_postprocess_icesheets.py
modules/gilford/icesheets/gilford_preprocess_icesheets.py
modules/gilford/icesheets/gilford_project_icesheets.py
modules/gilford/icesheets/reconstruct_emulator.ipynb
modules/gilford/icesheets/sample_emulator.py
modules/kopp14/glaciers/AssignFP.py
modules/kopp14/glaciers/ReadFingerprint.py
modules/kopp14/glaciers/cholcov.py
modules/kopp14/glaciers/kopp14_fit_glaciers.py
modules/kopp14/glaciers/kopp14_postprocess_glaciers.py
modules/kopp14/glaciers/kopp14_preprocess_glaciers.py
modules/kopp14/glaciers/kopp14_project_glaciers.py
modules/kopp14/glaciers/pipeline.yml
modules/kopp14/glaciers/readMarzeion.py
modules/kopp14/glaciers/read_bkgdrate.py
modules/kopp14/glaciers/readme
modules/kopp14/icesheets/AssignFP.py
modules/kopp14/icesheets/CalcISDists.py
modules/kopp14/icesheets/FitLNDistQuants.py
modules/kopp14/icesheets/ProjectGSL.py
modules/kopp14/icesheets/ReadFingerprint.py
modules/kopp14/icesheets/SampleISDists.py
modules/kopp14/icesheets/cholcov.py
modules/kopp14/icesheets/kopp14_fit_icesheets.py
modules/kopp14/icesheets/kopp14_postprocess_icesheets.py
modules/kopp14/icesheets/kopp14_preprocess_icesheets.py
modules/kopp14/icesheets/kopp14_project_icesheets.py
modules/kopp14/icesheets/pipeline.yml
modules/kopp14/icesheets/read_bkgdrate.py
modules/kopp14/landwaterstorage/kopp14_fit_landwaterstorage.py
modules/kopp14/landwaterstorage/kopp14_postprocess_landwaterstorage.py
modules/kopp14/landwaterstorage/kopp14_preprocess_landwaterstorage.py
modules/kopp14/landwaterstorage/kopp14_project_landwaterstorage.py
modules/kopp14/landwaterstorage/pipeline.yml
src/radical.facts.egg-info/PKG-INFO
src/radical.facts.egg-info/SOURCES.txt
src/radical.facts.egg-info/dependency_links.txt
src/radical.facts.egg-info/not-zip-safe
src/radical.facts.egg-info/top_level.txt