Metadata-Version: 1.1
Name: radical.facts
Version: 0.2.0
Summary: Framework for Assessing Changes To Sea-level (FACTS)
Home-page: https://github.com/radical-collaboration/facts.git
Author: Gregory Garner
Author-email: gregory.garner@rutgers.edu
License: unlicensed
Keywords: radical facts
Platform: UNKNOWN
Classifier: Programming Language :: Python :: 2
Classifier: Programming Language :: Python :: 2.7
Classifier: Topic :: Utilities
Classifier: Topic :: System :: Distributed Computing
Classifier: Topic :: Scientific/Engineering
Classifier: Operating System :: MacOS :: MacOS X
Classifier: Operating System :: POSIX
Classifier: Operating System :: Unix
